{
  "name": "Bloons TD 6",
  "category": "Games",
  "rating": 8.9,
  "wouldRecommend": true,
  "summary": "The best TD game out there IMO. Perfect blend of whismy fun and highly technical strategy making.",
  "pros": [
    "Very fun monkeys",
    "Strategising for different maps is always fun",
    "Good music"
  ],
  "cons": [
    "A bit too cluttered off-late? Too many power-ups and out of control power creep IMO"
  ],
  "link": "https://ninjakiwi.com/Games/Mobile/Bloons-TD-6.html",
  "reviewDate": "2022-02-08T18:30:00.000Z"
}